nbnlp/__init__.py
nbnlp/api.py
nbnlp/db.py
nbnlp/model.py
nbnlp/ner.py
nbnlp/scheduler.py
nbnlp/utils.py
nbnlp/data/test.tsv
nbnlp/data/train.tsv
nbnlp-3.0.0.dist-info/LICENSE
nbnlp-3.0.0.dist-info/METADATA
nbnlp-3.0.0.dist-info/WHEEL
nbnlp-3.0.0.dist-info/top_level.txt
nbnlp-3.0.0.dist-info/RECORD
